threatbus/__init__.py
threatbus/appspecs.py
threatbus/backbonespecs.py
threatbus/data.py
threatbus/logger.py
threatbus/stix2_helpers.py
threatbus/stoppable_worker.py
threatbus/subscriptions.py
threatbus/test_data.py
threatbus/test_stix2_helpers.py
threatbus/threatbus.py
threatbus-2022.5.16.dist-info/COPYING
threatbus-2022.5.16.dist-info/METADATA
threatbus-2022.5.16.dist-info/WHEEL
threatbus-2022.5.16.dist-info/entry_points.txt
threatbus-2022.5.16.dist-info/top_level.txt
threatbus-2022.5.16.dist-info/RECORD
