Metadata-Version: 2.1
Name: threatbus
Version: 2022.5.16
Summary: The missing link to connect open-source threat intelligence tools.
Home-page: https://github.com/tenzir/threatbus
Author: Tenzir
Author-email: engineering@tenzir.com
License: BSD 3-clause
Keywords: threatbus,threat intelligence,intel,sightings,open source threat intelligence
Platform: UNKNOWN
Classifier: Development Status :: 4 - Beta
Classifier: Environment :: Plugins
Classifier: License :: OSI Approved :: BSD License
Classifier: Operating System :: MacOS :: MacOS X
Classifier: Operating System :: POSIX :: Linux
Classifier: Topic :: Scientific/Engineering :: Information Analysis
Classifier: Topic :: Scientific/Engineering :: Interface Engine/Protocol Translator
Classifier: Topic :: Security
Classifier: Topic :: Software Development :: Object Brokering
Classifier: Topic :: System :: Distributed Computing
Requires-Python: >=3.7
Requires-Dist: black (>=19.10b)
Requires-Dist: coloredlogs (>=10.0)
Requires-Dist: dynaconf (!=3.1.8,>=3.1.4)
Requires-Dist: pluggy (>=0.13)
Requires-Dist: python-dateutil (>=2.8.1)
Requires-Dist: stix2-patterns (==1.3.0)
Requires-Dist: stix2 (>=3.0)
